assessment_episode_matcher/MyDataframe.py
assessment_episode_matcher/__init__.py
assessment_episode_matcher/audits.py
assessment_episode_matcher/data_config.py
assessment_episode_matcher/data_prep.py
assessment_episode_matcher/mytypes.py
assessment_episode_matcher/nada.py
assessment_episode_matcher/test_surveytxt.py
assessment_episode_matcher/test_surveytxt_local.py
assessment_episode_matcher/version.py
assessment_episode_matcher/azutil/__init__.py
assessment_episode_matcher/azutil/az_blob_query.py
assessment_episode_matcher/azutil/az_tables_query.py
assessment_episode_matcher/azutil/file_types.py
assessment_episode_matcher/azutil/helper.py
assessment_episode_matcher/configs/__init__.py
assessment_episode_matcher/configs/audit.py
assessment_episode_matcher/configs/constants.py
assessment_episode_matcher/configs/episodes.py
assessment_episode_matcher/exporters/NADAbase.py
assessment_episode_matcher/exporters/__init__.py
assessment_episode_matcher/exporters/main.py
assessment_episode_matcher/exporters/config/NADAbase.py
assessment_episode_matcher/exporters/config/__init__.py
assessment_episode_matcher/importers/__init__.py
assessment_episode_matcher/importers/aod.py
assessment_episode_matcher/importers/assessments.py
assessment_episode_matcher/importers/episodes.py
assessment_episode_matcher/importers/main.py
assessment_episode_matcher/importers/nada_eps_export.py
assessment_episode_matcher/importers/nada_indexed.py
assessment_episode_matcher/matching/__init__.py
assessment_episode_matcher/matching/date_checks.py
assessment_episode_matcher/matching/errors.py
assessment_episode_matcher/matching/increasing_slack.py
assessment_episode_matcher/matching/main.py
assessment_episode_matcher/matching/matching_stats.py
assessment_episode_matcher/setup/__init__.py
assessment_episode_matcher/setup/bootstrap.py
assessment_episode_matcher/setup/log_management.py
assessment_episode_matcher/utils/__init__.py
assessment_episode_matcher/utils/base.py
assessment_episode_matcher-0.7.0.dist-info/LICENSE
assessment_episode_matcher-0.7.0.dist-info/METADATA
assessment_episode_matcher-0.7.0.dist-info/WHEEL
assessment_episode_matcher-0.7.0.dist-info/top_level.txt
assessment_episode_matcher-0.7.0.dist-info/RECORD
