Metadata-Version: 2.2
Name: assessment_episode_matcher
Version: 0.7.0
Author: Aftab Jalal
Author-email: mj@auditlytics.nz
License: MIT
Classifier: Programming Language :: Python :: 3
Classifier: License :: OSI Approved :: MIT License
Classifier: Operating System :: OS Independent
Requires-Python: >=3.10
License-File: LICENSE
Requires-Dist: python-dotenv==1.0.1
Requires-Dist: pandas==2.2.2
Requires-Dist: pyarrow==16.1.0
Requires-Dist: azure_data_tables==12.5.0
Requires-Dist: azure_storage_blob==12.20.0
Requires-Dist: rapidfuzz==3.9.3
Dynamic: author
Dynamic: author-email
Dynamic: classifier
Dynamic: license
Dynamic: requires-dist
Dynamic: requires-python
